afterbuild/__init__.py
afterbuild/core.py
afterbuild/bin/pyi-archive_viewer.exe
afterbuild/bin/pyi-bindepend.exe
afterbuild/bin/pyi-grab_version.exe
afterbuild/bin/pyi-makespec.exe
afterbuild/bin/pyi-set_version.exe
afterbuild/bin/pyinstaller.exe
afterbuild-1.7.1.dist-info/METADATA
afterbuild-1.7.1.dist-info/WHEEL
afterbuild-1.7.1.dist-info/top_level.txt
afterbuild-1.7.1.dist-info/RECORD
