Metadata-Version: 2.4
Name: afterbuild
Version: 1.7.1
Summary: Professional Standalone Executable Builder
Author: Your Name
Classifier: Programming Language :: Python :: 3
Classifier: License :: OSI Approved :: MIT License
Classifier: Operating System :: Microsoft :: Windows
Dynamic: author
Dynamic: classifier
Dynamic: description-content-type
Dynamic: summary
